message_subscriber/__init__.py
message_subscriber/example.py
message_subscriber/frontend/build/asset-manifest.json
message_subscriber/frontend/build/index.html
message_subscriber/frontend/build/static/js/main.02661d8e.js
message_subscriber/frontend/build/static/js/main.02661d8e.js.LICENSE.txt
message_subscriber/frontend/build/static/js/main.02661d8e.js.map
message_subscriber/frontend/build/static/js/main.475c90de.js
message_subscriber/frontend/build/static/js/main.475c90de.js.LICENSE.txt
message_subscriber/frontend/build/static/js/main.475c90de.js.map
message_subscriber/frontend/build/static/js/main.96cdb41a.js
message_subscriber/frontend/build/static/js/main.96cdb41a.js.LICENSE.txt
message_subscriber/frontend/build/static/js/main.96cdb41a.js.map
message_subscriber-0.0.4.dist-info/METADATA
message_subscriber-0.0.4.dist-info/WHEEL
message_subscriber-0.0.4.dist-info/top_level.txt
message_subscriber-0.0.4.dist-info/RECORD
