Metadata-Version: 2.4
Name: message_subscriber
Version: 0.0.4
Summary: Streamlit component that allows you to subscribe to messages
Home-page: 
Author: Qishi
Author-email: hongfeizhan@qq.com
Requires-Python: >=3.11
Requires-Dist: streamlit>=1.41.1
Provides-Extra: devel
Requires-Dist: wheel; extra == "devel"
Requires-Dist: pytest==7.4.0; extra == "devel"
Requires-Dist: playwright==1.48.0; extra == "devel"
Requires-Dist: requests==2.31.0; extra == "devel"
Requires-Dist: pytest-playwright-snapshot==1.0; extra == "devel"
Requires-Dist: pytest-rerunfailures==12.0; extra == "devel"
Dynamic: author
Dynamic: author-email
Dynamic: description
Dynamic: description-content-type
Dynamic: provides-extra
Dynamic: requires-dist
Dynamic: requires-python
Dynamic: summary
